.bumpversion.cfg
.codeclimate.yml
.gitignore
.gitmodules
.travis.yml
COPYING
README.md
README.rst
requirements.in
requirements.txt
setup.py
wercker.yml
dataset_io/__init__.py
dataset_io/constants.py
dataset_io/helper.py
dataset_io/loader.py
dataset_io/rating.csv
dataset_io/resume.py
dataset_io/sampler.py
docs/.gitignore
docs/Makefile
docs/source/_templates
docs/source/conf.py
docs/source/index.rst
docs/source/_static/image.png
misc/index.html
rgmining_dataset_io.egg-info/PKG-INFO
rgmining_dataset_io.egg-info/SOURCES.txt
rgmining_dataset_io.egg-info/dependency_links.txt
rgmining_dataset_io.egg-info/requires.txt
rgmining_dataset_io.egg-info/top_level.txt
tests/__init__.py
tests/helper_test.py
tests/loader_test.py
tests/mock.py
tests/resume_test.py
tests/sampler_test.py
tests/test_suite.py